feedstail-0.5.1.data/data/README.rst
feedstail-0.5.1.data/data/LICENSE.txt
feedstail-0.5.1.data/scripts/feedstail
feedstail/utils.py
feedstail/config.py
feedstail/feedstail.py
feedstail/__init__.py
feedstail-0.5.1.dist-info/METADATA
feedstail-0.5.1.dist-info/WHEEL
feedstail-0.5.1.dist-info/RECORD
feedstail-0.5.1.dist-info/top_level.txt
feedstail-0.5.1.dist-info/pydist.json
feedstail-0.5.1.dist-info/DESCRIPTION.rst
