Metadata-Version: 2.0
Name: feedstail
Version: 0.5.1
Summary: A tail-f-like utility for feeds
Home-page: https://github.com/Psycojoker/feedstail
Author: Romain Gauthier
Author-email: romain.gauthier@masteri2l.org
License: GNU General Public License v3
Platform: UNKNOWN
Classifier: Development Status :: 3 - Alpha
Classifier: License :: OSI Approved :: GNU General Public License (GPL)
Classifier: Operating System :: OS Independent
Classifier: Programming Language :: Python :: 2.7
Classifier: Topic :: Utilities
Requires-Dist: argparse
Requires-Dist: FeedParser
